<XML>
    <Produtos>
        <Prod1>
            <Nome>teste1</Nome>
            <Codigo>45</Codigo>
            <Custo>5450,50</Custo>
            <Venda>50,00</Venda>
        </Prod1>
        <Prod2>
            <Nome>teste5</Nome>
            <Codigo>673</Codigo>
            <Custo>550,10</Custo>
            <Venda>10,50</Venda>
        </Prod2>
        <Prod3>
            <Nome>teste2</Nome>
            <Codigo>567</Codigo>
            <Custo>45,00</Custo>
            <Venda>65,00</Venda>
        </Prod3>
        <Prod4>
            <Nome>teste4</Nome>
            <Codigo>1324</Codigo>
            <Custo>57,00</Custo>
            <Venda>89,99</Venda>
        </Prod4>
        <Prod5>
            <Nome>teste10</Nome>
            <Codigo>567</Codigo>
            <Custo>43,00</Custo>
            <Venda>56,00</Venda>
        </Prod5>
        <Prod6>
            <Nome>teste7</Nome>
            <Codigo>456</Codigo>
            <Custo>1,00</Custo>
            <Venda>3,00</Venda>
        </Prod6>
        <Prod7>
            <Nome>fgfg</Nome>
            <Codigo>674</Codigo>
            <Custo>34,00</Custo>
            <Venda>56,00</Venda>
        </Prod7>
        <Prod8>
            <Nome>ytytyy</Nome>
            <Codigo>535325</Codigo>
            <Custo>345,00</Custo>
            <Venda>45,00</Venda>
        </Prod8>
        <Prod9>
            <Nome>ygscge</Nome>
            <Codigo>42462</Codigo>
            <Custo>3,00</Custo>
            <Venda>5,00</Venda>
        </Prod9>
        <Prod10>
            <Nome>ygdcge</Nome>
            <Codigo>564</Codigo>
            <Custo>3,50</Custo>
            <Venda>5,00</Venda>
        </Prod10>
    </Produtos>
</XML>
